consistentor/__init__.py
consistentor/rendezvous.py
consistentor/selector.py
consistentor-0.1.0.dist-info/LICENSE
consistentor-0.1.0.dist-info/METADATA
consistentor-0.1.0.dist-info/WHEEL
consistentor-0.1.0.dist-info/top_level.txt
consistentor-0.1.0.dist-info/RECORD
