Metadata-Version: 2.1
Name: consistentor
Version: 0.1.0
Summary: Consistentor helps you select things consistently
Home-page: https://github.com/jannekem/consistentor
Author: Janne Kemppainen
License: MIT
Platform: UNKNOWN
Classifier: Development Status :: 3 - Alpha
Classifier: License :: OSI Approved :: MIT License
Classifier: Topic :: Software Development :: Libraries
Requires-Python: >=3.6.0
Requires-Dist: xxhash
